setup.py
tcpstat/__init__.py
tcpstat/tcpstat.py
tcpstat.egg-info/PKG-INFO
tcpstat.egg-info/SOURCES.txt
tcpstat.egg-info/dependency_links.txt
tcpstat.egg-info/entry_points.txt
tcpstat.egg-info/requires.txt
tcpstat.egg-info/top_level.txt