Metadata-Version: 1.1
Name: tcpstat
Version: 0.0.1
Summary: A TCP port traffic monitor.
Home-page: https://github.com/caizixian/tcpstat
Author: Ivan Cai
Author-email: caizixian@users.noreply.github.com
License: MIT
Keywords: traffic accounting network
Platform: UNKNOWN
Classifier: Development Status :: 3 - Alpha
Classifier: Intended Audience :: System Administrators
Classifier: Intended Audience :: Developers
Classifier: Topic :: System :: Networking :: Monitoring
Classifier: License :: OSI Approved :: MIT License
Classifier: Programming Language :: Python :: 2
Classifier: Programming Language :: Python :: 2.6
Classifier: Programming Language :: Python :: 2.7
Classifier: Programming Language :: Python :: 3
Classifier: Programming Language :: Python :: 3.3
Classifier: Programming Language :: Python :: 3.4
Classifier: Operating System :: POSIX :: Linux
